sleeper_wrapper/__init__.py
sleeper_wrapper/base_api.py
sleeper_wrapper/drafts.py
sleeper_wrapper/league.py
sleeper_wrapper/players.py
sleeper_wrapper/stats.py
sleeper_wrapper/user.py
sleeper_api_wrapper-1.0.7.dist-info/LICENSE.md
sleeper_api_wrapper-1.0.7.dist-info/METADATA
sleeper_api_wrapper-1.0.7.dist-info/WHEEL
sleeper_api_wrapper-1.0.7.dist-info/top_level.txt
sleeper_api_wrapper-1.0.7.dist-info/RECORD
