Metadata-Version: 2.1
Name: sleeper-api-wrapper
Version: 1.0.7
Summary: A Python API wrapper for Sleeper Fantasy Football, as well as tools to simplify data recieved.
Home-page: https://github.com/SwapnikKatkoori/sleeper-api-wrapper
Author: Swapnik Katkoori
Author-email: katkoor2@msu.edu
License: MIT
Platform: UNKNOWN
Classifier: License :: OSI Approved :: MIT License
Classifier: Programming Language :: Python :: 3.5
Classifier: Programming Language :: Python :: 3.7
